t3tokit/__init__.py
t3tokit/mzip.py
t3tokit/voice_zhipu.py
t3tokit-0.1.2.dist-info/WHEEL
t3tokit-0.1.2.dist-info/METADATA
t3tokit-0.1.2.dist-info/RECORD
