Metadata-Version: 2.1
Name: t3tokit
Version: 0.1.2
Summary: A simple utility for creating directories.
License: MIT
Author: pytools
Author-email: hyhlinux@gmail.com
Requires-Python: >=3.8,<4.0
Classifier: License :: OSI Approved :: MIT License
Classifier: Programming Language :: Python :: 3
Classifier: Programming Language :: Python :: 3.8
Classifier: Programming Language :: Python :: 3.9
Classifier: Programming Language :: Python :: 3.10
Classifier: Programming Language :: Python :: 3.11
